{
  "ClientType": "1",
  "ClientId": "masa.stack.web-staging",
  "ClientName": "Masa Stack Web(Staging)",
  "AllowedScopes": [
    "openid",
    "profile"
  ],
  "RedirectUris": [
    "https://auth-staging.masastack.com/signin-oidc",
    "http://auth-staging.masastack.com/signin-oidc",
    "http://pm-staging.masastack.com/signin-oidc",
    "https://pm-staging.masastack.com/signin-oidc",
    "https://dcc-staging.masastack.com/signin-oidc",
    "http://dcc-staging.masastack.com/signin-oidc",
    "https://mc-staging.masastack.com/signin-oidc",
    "http://mc-staging.masastack.com/signin-oidc",
    "https://tsc-staging.masastack.com/signin-oidc",
    "http://tsc-staging.masastack.com/signin-oidc",
    "https://scheduler-staging.masastack.com/signin-oidc",
    "http://scheduler-staging.masastack.com/signin-oidc"
  ],
  "PostLogoutRedirectUris": [
    "https://auth-staging.masastack.com/signout-callback-oidc",
    "http://auth-staging.masastack.com/signout-callback-oidc",
    "http://pm-staging.masastack.com/signout-callback-oidc",
    "https://pm-staging.masastack.com/signout-callback-oidc",
    "https://dcc-staging.masastack.com/signout-callback-oidc",
    "http://dcc-staging.masastack.com/signout-callback-oidc",
    "https://mc-staging.masastack.com/signout-callback-oidc",
    "http://mc-staging.masastack.com/signout-callback-oidc",
    "https://tsc-staging.masastack.com/signout-callback-oidc",
    "http://tsc-staging.masastack.com/signout-callback-oidc",
    "https://scheduler-staging.masastack.com/signout-callback-oidc",
    "http://scheduler-staging.masastack.com/signout-callback-oidc"
  ]
}